nsync/__init__.py
nsync/client.py
nsync/home.html
nsync/main.py
nsync/server.py
neutron_sync-1.0.0.dist-info/entry_points.txt
neutron_sync-1.0.0.dist-info/WHEEL
neutron_sync-1.0.0.dist-info/METADATA
neutron_sync-1.0.0.dist-info/licenses/LICENSE
neutron_sync-1.0.0.dist-info/RECORD
